[
    {
        "code": "ld hl,**",
        "destroys": "HL",
        "input": "",
        "ir": "\\constant",
        "output": "HL=o1=uint16",
        "requires": "",
        "size": 3,
        "speed": 10,
        "state": ""
    },
    {
        "code": "ld de,**",
        "destroys": "DE",
        "input": "",
        "ir": "\\constant",
        "output": "DE=o1=uint16",
        "requires": "",
        "size": 3,
        "speed": 10,
        "state": ""
    },
    {
        "code": "ld bc,**",
        "destroys": "BC",
        "input": "",
        "ir": "\\constant",
        "output": "BC=o1=uint16",
        "requires": "",
        "size": 3,
        "speed": 10,
        "state": ""
    },
    {
        "code": "ld ix,**",
        "destroys": "IX",
        "input": "",
        "ir": "\\constant",
        "output": "IX=o1=uint16",
        "requires": "",
        "size": 4,
        "speed": 14,
        "state": ""
    },
    {
        "code": "add hl,hl",
        "destroys": "HL,cf",
        "input": "HL=i1=uint16",
        "ir": "1 <<",
        "output": "cf:HL=o1=uint17",
        "requires": "",
        "size": 1,
        "speed": 11,
        "state": ""
    },
    {
        "code": "sla e \\ rl d",
        "destroys": "DE,cf",
        "input": "DE=i1=uint16",
        "ir": "1 <<",
        "output": "cf:DE=o1=uint17",
        "requires": "",
        "size": 4,
        "speed": 16,
        "state": ""
    },
    {
        "code": "sla c \\ rl b",
        "destroys": "BC,cf",
        "input": "BC=i1=uint16",
        "ir": "1 <<",
        "output": "cf:BC=o1=uint17",
        "requires": "",
        "size": 4,
        "speed": 16,
        "state": ""
    },
    {
        "code": "add ix,ix",
        "destroys": "IX,cf",
        "input": "IX=i1=uint16",
        "ir": "1 <<",
        "output": "cf:IX=o1=uint17",
        "requires": "",
        "size": 2,
        "speed": 15,
        "state": ""
    },
    {
        "code": "add hl,hl \\ inc l",
        "destroys": "HL,cf",
        "input": "HL=i1=uint16",
        "ir": "1 << ++",
        "output": "cf:HL=o1=uint17",
        "requires": "",
        "size": 2,
        "speed": 15,
        "state": ""
    },
    {
        "code": "sll e \\ rl d",
        "destroys": "DE,cf",
        "input": "DE=i1=uint16",
        "ir": "1 << ++",
        "output": "cf:DE=o1=uint17",
        "requires": "#ifdef USE_UNDOCUMENTED",
        "size": 4,
        "speed": 16,
        "state": ""
    },
    {
        "code": "sll c \\ rl b",
        "destroys": "BC,cf",
        "input": "BC=i1=uint16",
        "ir": "1 << ++",
        "output": "cf:BC=o1=uint17",
        "requires": "#ifdef USE_UNDOCUMENTED",
        "size": 4,
        "speed": 16,
        "state": ""
    },
    {
        "code": "add ix,ix \\ inc ixl",
        "destroys": "IX,cf",
        "input": "IX=i1=uint16",
        "ir": "1 << ++",
        "output": "cf:IX=o1=uint17",
        "requires": "",
        "size": 4,
        "speed": 23,
        "state": ""
    },
    {
        "code": "call mulHLDE",
        "destroys": "AF,HL,DE,BC",
        "input": "HL=i1=uint16, DE=i2=uint16",
        "ir": "*",
        "output": "DE:HL=o1=uint32",
        "requires": "#include mulHLDE.z80",
        "size": 3,
        "speed": 561.887,
        "state": ""
    },
    {
        "code": "call mulHLDE",
        "destroys": "AF,HL,DE,BC",
        "input": "DE=i1=uint16, HL=i2=uint16",
        "ir": "*",
        "output": "DE:HL=o1=uint32",
        "requires": "#include mulHLDE.z80",
        "size": 3,
        "speed": 561.887,
        "state": ""
    },
    {
        "code": "ld b,h \\ ld c,l \\ add hl,hl \\ add hl,bc \\ add hl,hl",
        "destroys": "BC,HL",
        "input": "HL=i1=uint16",
        "ir": "6 *",
        "output": "HL=o1=uint16",
        "requires": "",
        "size": 5,
        "speed": 41,
        "state": "BC=i1"
    },
    {
        "code": "ld h,d \\ ld h,e \\ add hl,hl \\ add hl,de \\ add hl,hl",
        "destroys": "HL,DE",
        "input": "DE=i1=uint16",
        "ir": "6 *",
        "output": "HL=o1=uint16",
        "requires": "",
        "size": 5,
        "speed": 41,
        "state": "DE=i1"
    },
    {
        "code": "ld h,b \\ ld l,c \\ add hl,hl \\ add hl,bc \\ add hl,hl",
        "destroys": "HL,BC",
        "input": "BC=i1=uint16",
        "ir": "6 *",
        "output": "HL=o1=uint16",
        "requires": "",
        "size": 5,
        "speed": 41,
        "state": "BC=i1"
    },
    {
        "code": "ld b,ixh \\ ld c,ixl \\ add ix,ix \\ add ix,bc \\ add ix,ix",
        "destroys": "BC,IX",
        "input": "IX=i1=uint16",
        "ir": "6 *",
        "output": "IX=o1=uint16",
        "requires": "",
        "size": 10,
        "speed": 61,
        "state": "BC=i1"
    },
    {
        "code": "ld b,ixh \\ ld c,ixl \\ ld h,b \\ ld l,c \\ add hl,hl \\ add hl,bc \\ add hl,hl",
        "destroys": "BC,IX,HL",
        "input": "IX=i1=uint16",
        "ir": "6 *",
        "output": "HL=o1=uint16",
        "requires": "",
        "size": 9,
        "speed": 57,
        "state": "BC=i1"
    },
    {
        "code": "inc hl",
        "destroys": "HL",
        "input": "HL=i1=uint16",
        "ir": "++",
        "output": "HL=o1=uint16",
        "requires": "",
        "size": 1,
        "speed": 6,
        "state": ""
    },
    {
        "code": "inc de",
        "destroys": "DE",
        "input": "DE=i1=uint16",
        "ir": "++",
        "output": "DE=o1=uint16",
        "requires": "",
        "size": 1,
        "speed": 6,
        "state": ""
    },
    {
        "code": "inc bc",
        "destroys": "BC",
        "input": "BC=i1=uint16",
        "ir": "++",
        "output": "BC=o1=uint16",
        "requires": "",
        "size": 1,
        "speed": 6,
        "state": ""
    },
    {
        "code": "inc ix",
        "destroys": "IX",
        "input": "IX=i1=uint16",
        "ir": "++",
        "output": "IX=o1=uint16",
        "requires": "",
        "size": 2,
        "speed": 10,
        "state": ""
    },
    {
        "code": "add hl,bc",
        "destroys": "HL",
        "input": "HL=i1=uint16, BC=i2=uint16",
        "ir": "+",
        "output": "cf:HL=o1=uint17",
        "requires": "",
        "size": 1,
        "speed": 11,
        "state": ""
    },
    {
        "code": "add hl,de",
        "destroys": "HL",
        "input": "HL=i1=uint16, DE=i2=uint16",
        "ir": "+",
        "output": "cf:HL=o1=uint17",
        "requires": "",
        "size": 1,
        "speed": 11,
        "state": ""
    },
    {
        "code": "add ix,bc",
        "destroys": "HL",
        "input": "IX=i1=uint16, BC=i2=uint16",
        "ir": "+",
        "output": "cf:IX=o1=uint17",
        "requires": "",
        "size": 2,
        "speed": 15,
        "state": ""
    },
    {
        "code": "add ix,de",
        "destroys": "HL",
        "input": "IX=i1=uint16, DE=i2=uint16",
        "ir": "+",
        "output": "cf:IX=o1=uint17",
        "requires": "",
        "size": 2,
        "speed": 15,
        "state": ""
    },
    {
        "code": "add hl,bc",
        "destroys": "IX",
        "input": "BC=i1=uint16, HL=i2=uint16",
        "ir": "+",
        "output": "cf:HL=o1=uint17",
        "requires": "",
        "size": 1,
        "speed": 11,
        "state": ""
    },
    {
        "code": "add hl,de",
        "destroys": "HL",
        "input": "DE=i1=uint16, HL=i2=uint16",
        "ir": "+",
        "output": "cf:HL=o1=uint17",
        "requires": "",
        "size": 1,
        "speed": 11,
        "state": ""
    },
    {
        "code": "add ix,bc",
        "destroys": "HL",
        "input": "BC=i1=uint16, IX=i2=uint16",
        "ir": "+",
        "output": "cf:IX=o1=uint17",
        "requires": "",
        "size": 2,
        "speed": 15,
        "state": ""
    },
    {
        "code": "add ix,de",
        "destroys": "HL",
        "input": "DE=i1=uint16, IX=i2=uint16",
        "ir": "+",
        "output": "cf:IX=o1=uint17",
        "requires": "",
        "size": 2,
        "speed": 15,
        "state": ""
    },
    {
        "code": "ld hl,(**)",
        "destroys": "HL",
        "input": "",
        "ir": "\\var",
        "output": "HL=o1=uint16",
        "requires": "",
        "size": 3,
        "speed": 16,
        "state": ""
    },
    {
        "code": "ld de,(**)",
        "destroys": "DE",
        "input": "",
        "ir": "\\var",
        "output": "DE=o1=uint16",
        "requires": "",
        "size": 4,
        "speed": 20,
        "state": ""
    },
    {
        "code": "ld bc,(**)",
        "destroys": "BC",
        "input": "",
        "ir": "\\var",
        "output": "BC=o1=uint16",
        "requires": "",
        "size": 4,
        "speed": 20,
        "state": ""
    },
    {
        "code": "ld ix,(**)",
        "destroys": "IX",
        "input": "",
        "ir": "\\var",
        "output": "IX=o1=uint16",
        "requires": "",
        "size": 4,
        "speed": 20,
        "state": ""
    },
    {
        "code": "ld (**),hl",
        "destroys": "",
        "input": "HL=i1=uint16",
        "ir": "\\sto",
        "output": "**=o1=uint16",
        "requires": "",
        "size": 3,
        "speed": 16,
        "state": ""
    },
    {
        "code": "ld (**),de",
        "destroys": "",
        "input": "DE=i1=uint16",
        "ir": "\\sto",
        "output": "**=o1=uint16",
        "requires": "",
        "size": 3,
        "speed": 20,
        "state": ""
    },
    {
        "code": "ld (**),bc",
        "destroys": "",
        "input": "BC=i1=uint16",
        "ir": "\\sto",
        "output": "**=o1=uint16",
        "requires": "",
        "size": 3,
        "speed": 20,
        "state": ""
    },
    {
        "code": "ld (**),ix",
        "destroys": "",
        "input": "IX=i1=uint16",
        "ir": "\\sto",
        "output": "**=o1=uint16",
        "requires": "",
        "size": 4,
        "speed": 20,
        "state": ""
    },
    {
        "code": "call disp_uint16",
        "destroys": "",
        "input": "HL=i1=uint16",
        "ir": "Disp(",
        "output": "",
        "requires": "#include \"disp_uint16.z80\"",
        "size": 3,
        "speed": 17,
        "state": ""
    },
    {
        "code": "add hl,hl \\ add hl,hl \\ inc l",
        "destroys": "HL",
        "input": "HL=i1=uint16",
        "ir": "2 << ++",
        "output": "cf:HL=o1=uint17",
        "requires": "",
        "size": 3,
        "speed": 26,
        "state": ""
    },
    {
        "code": "sla e \\ rl d \\ sll e \\ rl d",
        "destroys": "DE",
        "input": "DE=i1=uint16",
        "ir": "2 << ++",
        "output": "cf:DE=o1=uint17",
        "requires": "#ifdef USE_UNDOCUMENTED",
        "size": 8,
        "speed": 32,
        "state": ""
    },
    {
        "code": "sla c \\ rl b \\ sll c \\ rl b",
        "destroys": "BC",
        "input": "BC=i1=uint16",
        "ir": "2 << ++",
        "output": "cf:BC=o1=uint17",
        "requires": "#ifdef USE_UNDOCUMENTED",
        "size": 8,
        "speed": 32,
        "state": ""
    },
    {
        "code": "add ix,ix \\ add ix,ix \\ inc ixl",
        "destroys": "IX",
        "input": "IX=i1=uint16",
        "ir": "2 << ++",
        "output": "cf:IX=o1=uint17",
        "requires": "",
        "size": 6,
        "speed": 38,
        "state": ""
    },
    {
        "code": "add hl,hl \\ add hl,hl",
        "destroys": "HL",
        "input": "HL=i1=uint16",
        "ir": "2 <<",
        "output": "cf:HL=o1=uint17",
        "requires": "",
        "size": 2,
        "speed": 22,
        "state": ""
    },
    {
        "code": "sla e \\ rl d \\ sla e \\ rl d",
        "destroys": "DE",
        "input": "DE=i1=uint16",
        "ir": "2 <<",
        "output": "cf:DE=o1=uint17",
        "requires": "",
        "size": 8,
        "speed": 32,
        "state": ""
    },
    {
        "code": "sla c \\ rl b \\ sla c \\ rl b",
        "destroys": "BC",
        "input": "BC=i1=uint16",
        "ir": "2 <<",
        "output": "cf:BC=o1=uint17",
        "requires": "",
        "size": 8,
        "speed": 32,
        "state": ""
    },
    {
        "code": "add ix,ix \\ add ix,ix",
        "destroys": "IX",
        "input": "IX=i1=uint16",
        "ir": "2 <<",
        "output": "cf:IX=o1=uint17",
        "requires": "",
        "size": 4,
        "speed": 30,
        "state": ""
    },
    {
        "code": "or a \\ sbc hl,bc",
        "destroys": "HL",
        "input": "BC=i1=uint16, HL=i2=uint16",
        "ir": "-",
        "output": "cf:HL=o1=uint17",
        "requires": "",
        "size": 3,
        "speed": 19,
        "state": ""
    },
    {
        "code": "or a \\ sbc hl,de",
        "destroys": "HL",
        "input": "DE=i1=uint16, HL=i2=uint16",
        "ir": "-",
        "output": "cf:HL=o1=uint17",
        "requires": "",
        "size": 3,
        "speed": 19,
        "state": ""
    },
    {
        "code": "ex de,hl \\ or a \\ sbc hl,de",
        "destroys": "DE,HL",
        "input": "HL=i1=uint16, DE=i2=uint16",
        "ir": "-",
        "output": "cf:HL=o1=uint17",
        "requires": "",
        "size": 4,
        "speed": 23,
        "state": ""
    },
    {
        "code": "ld b,h \\ ld c,l \\ add hl,hl \\ add hl,bc",
        "destroys": "HL,BC",
        "input": "HL=i1=uint16",
        "ir": "3 *",
        "output": "HL=o1=uint16",
        "requires": "",
        "size": 4,
        "speed": 30,
        "state": "BC=i1"
    },
    {
        "code": "ld h,d \\ ld h,e \\ add hl,hl \\ add hl,de",
        "destroys": "HL,DE",
        "input": "DE=i1=uint16",
        "ir": "3 *",
        "output": "HL=o1=uint16",
        "requires": "",
        "size": 4,
        "speed": 30,
        "state": "DE=i1"
    },
    {
        "code": "ld h,b \\ ld l,c \\ add hl,hl \\ add hl,bc",
        "destroys": "HL,BC",
        "input": "BC=i1=uint16",
        "ir": "3 *",
        "output": "HL=o1=uint16",
        "requires": "",
        "size": 4,
        "speed": 30,
        "state": "BC=i1"
    },
    {
        "code": "ld b,ixh \\ ld c,ixl \\ add ix,ix \\ add ix,bc",
        "destroys": "IX,BC",
        "input": "IX=i1=uint16",
        "ir": "3 *",
        "output": "IX=o1=uint16",
        "requires": "",
        "size": 8,
        "speed": 46,
        "state": "BC=i1"
    },
    {
        "code": "ld b,ixh \\ ld c,ixl \\ ld h,b \\ ld l,c \\ add hl,hl \\ add hl,bc",
        "destroys": "IX,BC,HL",
        "input": "IX=i1=uint16",
        "ir": "3 *",
        "output": "HL=o1=uint16",
        "requires": "",
        "size": 8,
        "speed": 46,
        "state": "BC=i1"
    },
    {
        "code": "ld b,h \\ ld c,l \\ add hl,hl \\ add hl,bc \\ add hl,hl \\ add hl,hl \\ add hl,hl \\ add hl,bc",
        "destroys": "HL,BC",
        "input": "HL=i1=uint16",
        "ir": "25 *",
        "output": "HL=o1=uint16",
        "requires": "",
        "size": 8,
        "speed": 74,
        "state": "BC=i1"
    },
    {
        "code": "ld h,d \\ ld h,e \\ add hl,hl \\ add hl,de \\ add hl,hl \\ add hl,hl \\ add hl,hl \\ add hl,de",
        "destroys": "HL,DE",
        "input": "DE=i1=uint16",
        "ir": "25 *",
        "output": "HL=o1=uint16",
        "requires": "",
        "size": 8,
        "speed": 74,
        "state": "DE=i1"
    },
    {
        "code": "ld h,b \\ ld l,c \\ add hl,hl \\ add hl,bc \\ add hl,hl \\ add hl,hl \\ add hl,hl \\ add hl,bc",
        "destroys": "HL,BC",
        "input": "BC=i1=uint16",
        "ir": "25 *",
        "output": "HL=o1=uint16",
        "requires": "",
        "size": 8,
        "speed": 74,
        "state": "BC=i1"
    },
    {
        "code": "ld b,ixh \\ ld c,ixl \\ add ix,ix \\ add ix,bc \\ add ix,ix \\ add ix,ix \\ add ix,ix \\ add ix,bc",
        "destroys": "IX,BC",
        "input": "IX=i1=uint16",
        "ir": "25 *",
        "output": "IX=o1=uint16",
        "requires": "",
        "size": 16,
        "speed": 106,
        "state": "BC=i1"
    },
    {
        "code": "ld b,ixh \\ ld c,ixl \\ ld h,b \\ ld l,c \\ add hl,hl \\ add hl,bc \\ add hl,hl \\ add hl,hl \\ add hl,hl \\ add hl,bc",
        "destroys": "IX,BC,HL",
        "input": "IX=i1=uint16",
        "ir": "25 *",
        "output": "HL=o1=uint16",
        "requires": "",
        "size": 12,
        "speed": 90,
        "state": "BC=i1"
    },
    {
        "code": "inc hl \\ inc hl",
        "destroys": "HL",
        "input": "HL=i1=uint16",
        "ir": "2 +",
        "output": "HL=o1=uint16",
        "requires": "",
        "size": 2,
        "speed": 12,
        "state": ""
    },
    {
        "code": "inc de \\ inc de",
        "destroys": "DE",
        "input": "DE=i1=uint16",
        "ir": "2 +",
        "output": "DE=o1=uint16",
        "requires": "",
        "size": 2,
        "speed": 12,
        "state": ""
    },
    {
        "code": "inc bc \\ inc bc",
        "destroys": "BC",
        "input": "BC=i1=uint16",
        "ir": "2 +",
        "output": "BC=o1=uint16",
        "requires": "",
        "size": 2,
        "speed": 12,
        "state": ""
    },
    {
        "code": "inc ix \\ inc ix",
        "destroys": "IX",
        "input": "IX=i1=uint16",
        "ir": "2 +",
        "output": "IX=o1=uint16",
        "requires": "",
        "size": 4,
        "speed": 20,
        "state": ""
    },
    {
        "code": "inc hl \\ inc hl \\ inc hl",
        "destroys": "HL",
        "input": "HL=i1=uint16",
        "ir": "3 +",
        "output": "HL=o1=uint16",
        "requires": "",
        "size": 3,
        "speed": 18,
        "state": ""
    },
    {
        "code": "inc de \\ inc de \\ inc de",
        "destroys": "DE",
        "input": "DE=i1=uint16",
        "ir": "3 +",
        "output": "DE=o1=uint16",
        "requires": "",
        "size": 3,
        "speed": 18,
        "state": ""
    },
    {
        "code": "inc bc \\ inc bc \\ inc bc",
        "destroys": "BC",
        "input": "BC=i1=uint16",
        "ir": "3 +",
        "output": "BC=o1=uint16",
        "requires": "",
        "size": 3,
        "speed": 18,
        "state": ""
    },
    {
        "code": "inc ix \\ inc ix \\ inc ix",
        "destroys": "IX",
        "input": "IX=i1=uint16",
        "ir": "3 +",
        "output": "IX=o1=uint16",
        "requires": "",
        "size": 6,
        "speed": 30,
        "state": ""
    },
    {
        "code": "add hl,hl \\ djnz $-1",
        "destroys": "B,HL,BC",
        "input": "HL=i1=uint16, B=i2=uint8",
        "ir": "<<",
        "output": "HL=o1=uint16",
        "requires": "",
        "size": 3,
        "speed": 187,
        "state": ""
    },
    {
        "code": "add hl,hl",
        "destroys": "",
        "input": "HL=i1=uint16",
        "ir": "<<[##,1",
        "output": "cf:HL=o1=uint17",
        "requires": "",
        "size": 1,
        "speed": 11,
        "state": ""
    },
    {
        "code": "sla e \\ rl d",
        "destroys": "",
        "input": "DE=i1=uint16",
        "ir": "<<[##,1",
        "output": "cf:DE=o1=uint17",
        "requires": "",
        "size": 4,
        "speed": 16,
        "state": ""
    },
    {
        "code": "sla c \\ rl b",
        "destroys": "",
        "input": "BC=i1=uint16",
        "ir": "<<[##,1",
        "output": "cf:BC=o1=uint17",
        "requires": "",
        "size": 4,
        "speed": 16,
        "state": ""
    },
    {
        "code": "add ix,ix",
        "destroys": "",
        "input": "IX=i1=uint16",
        "ir": "<<[##,1",
        "output": "cf:IX=o1=uint17",
        "requires": "",
        "size": 2,
        "speed": 15,
        "state": ""
    },
    {
        "code": "ld h,**",
        "destroys": "HL",
        "input": "",
        "ir": "\\constant",
        "output": "H=o1=uint8",
        "requires": "",
        "size": 2,
        "speed": 7,
        "state": ""
    },
    {
        "code": "ld d,**",
        "destroys": "DE",
        "input": "",
        "ir": "\\constant",
        "output": "D=o1=uint8",
        "requires": "",
        "size": 2,
        "speed": 7,
        "state": ""
    },
    {
        "code": "ld b,**",
        "destroys": "BC",
        "input": "",
        "ir": "\\constant",
        "output": "B=o1=uint8",
        "requires": "",
        "size": 2,
        "speed": 7,
        "state": ""
    },
    {
        "code": "ld ixh,**",
        "destroys": "IX",
        "input": "",
        "ir": "\\constant",
        "output": "IXH=o1=uint8",
        "requires": "",
        "size": 3,
        "speed": 11,
        "state": ""
    },
    {
        "code": "ld l,**",
        "destroys": "HL",
        "input": "",
        "ir": "\\constant",
        "output": "L=o1=uint8",
        "requires": "",
        "size": 2,
        "speed": 7,
        "state": ""
    },
    {
        "code": "ld e,**",
        "destroys": "DE",
        "input": "",
        "ir": "\\constant",
        "output": "E=o1=uint8",
        "requires": "",
        "size": 2,
        "speed": 7,
        "state": ""
    },
    {
        "code": "ld c,**",
        "destroys": "BC",
        "input": "",
        "ir": "\\constant",
        "output": "C=o1=uint8",
        "requires": "",
        "size": 2,
        "speed": 7,
        "state": ""
    },
    {
        "code": "ld ixl,**",
        "destroys": "IX",
        "input": "",
        "ir": "\\constant",
        "output": "IXL=o1=uint8",
        "requires": "",
        "size": 3,
        "speed": 11,
        "state": ""
    },
    {
        "code": "ld a,**",
        "destroys": "AF",
        "input": "",
        "ir": "\\constant",
        "output": "A=o1=uint8",
        "requires": "",
        "size": 2,
        "speed": 7,
        "state": ""
    },
    {
        "code": "add hl,hl \\ djnz $-1 \\ inc l",
        "destroys": "B,HL,BC",
        "input": "HL=i1=uint16, B=i2=uint8",
        "ir": "<< ++",
        "output": "HL=o1=uint16",
        "requires": "",
        "size": 4,
        "speed": 191,
        "state": ""
    },
    {
        "code": "add hl,hl \\ add hl,hl \\ add hl,hl \\ inc l",
        "destroys": "HL",
        "input": "HL=i1=uint16",
        "ir": "3 << ++",
        "output": "cf:HL=o1=uint17",
        "requires": "",
        "size": 4,
        "speed": 37,
        "state": ""
    },
    {
        "code": "add hl,hl \\ add hl,hl \\ add hl,hl \\ add hl,hl \\ inc l",
        "destroys": "HL",
        "input": "HL=i1=uint16",
        "ir": "4 << ++",
        "output": "cf:HL=o1=uint17",
        "requires": "",
        "size": 5,
        "speed": 48,
        "state": ""
    },
    {
        "code": "add hl,hl \\ add hl,hl \\ add hl,hl \\ add hl,hl \\ add hl,hl \\ inc l",
        "destroys": "HL",
        "input": "HL=i1=uint16",
        "ir": "5 << ++",
        "output": "cf:HL=o1=uint17",
        "requires": "",
        "size": 6,
        "speed": 59,
        "state": ""
    },
    {
        "code": "add hl,hl \\ add hl,hl \\ add hl,hl \\ add hl,hl \\ add hl,hl \\ add hl,hl \\ inc l",
        "destroys": "HL",
        "input": "HL=i1=uint16",
        "ir": "6 << ++",
        "output": "cf:HL=o1=uint17",
        "requires": "",
        "size": 7,
        "speed": 70,
        "state": ""
    },
    {
        "code": "add hl,hl \\ add hl,hl \\ add hl,hl \\ add hl,hl \\ add hl,hl \\ add hl,hl \\ add hl,hl \\ inc l",
        "destroys": "HL",
        "input": "HL=i1=uint16",
        "ir": "7 << ++",
        "output": "cf:HL=o1=uint17",
        "requires": "",
        "size": 8,
        "speed": 81,
        "state": ""
    },
    {
        "code": "ld h,l \\ ld l,1",
        "destroys": "HL",
        "input": "HL=i1=uint16",
        "ir": "8 << ++",
        "output": "cf:HL=o1=uint17",
        "requires": "",
        "size": 3,
        "speed": 11,
        "state": ""
    },
    {
        "code": "ld h,l \\ ld l,0 \\ add hl,hl \\ inc l",
        "destroys": "HL",
        "input": "HL=i1=uint16",
        "ir": "9 << ++",
        "output": "cf:HL=o1=uint17",
        "requires": "",
        "size": 5,
        "speed": 26,
        "state": ""
    },
    {
        "code": "sra h \\ ld h,l \\ rr h \\ ld l,2 \\ rr l",
        "destroys": "HL",
        "input": "HL=i1=uint16",
        "ir": "7 << ++",
        "output": "cf:HL=o1=uint17",
        "requires": "",
        "size": 9,
        "speed": 35,
        "state": ""
    },
    {
        "code": "ld h,l \\ ld l,0 \\ add hl,hl \\ add hl,hl \\ inc l",
        "destroys": "HL",
        "input": "HL=i1=uint16",
        "ir": "10 << ++",
        "output": "cf:HL=o1=uint17",
        "requires": "",
        "size": 6,
        "speed": 37,
        "state": ""
    },
    {
        "code": "add hl,hl \\ add hl,hl \\ add hl,hl",
        "destroys": "HL",
        "input": "HL=i1=uint16",
        "ir": "3 <<",
        "output": "cf:HL=o1=uint17",
        "requires": "",
        "size": 3,
        "speed": 33,
        "state": ""
    },
    {
        "code": "add hl,hl \\ add hl,hl \\ add hl,hl \\ add hl,hl",
        "destroys": "HL",
        "input": "HL=i1=uint16",
        "ir": "4 <<",
        "output": "cf:HL=o1=uint17",
        "requires": "",
        "size": 4,
        "speed": 44,
        "state": ""
    },
    {
        "code": "add hl,hl \\ add hl,hl \\ add hl,hl \\ add hl,hl \\ add hl,hl",
        "destroys": "HL",
        "input": "HL=i1=uint16",
        "ir": "5 <<",
        "output": "cf:HL=o1=uint17",
        "requires": "",
        "size": 5,
        "speed": 55,
        "state": ""
    },
    {
        "code": "add hl,hl \\ add hl,hl \\ add hl,hl \\ add hl,hl \\ add hl,hl \\ add hl,hl",
        "destroys": "HL",
        "input": "HL=i1=uint16",
        "ir": "6 <<",
        "output": "cf:HL=o1=uint17",
        "requires": "",
        "size": 6,
        "speed": 66,
        "state": ""
    },
    {
        "code": "add hl,hl \\ add hl,hl \\ add hl,hl \\ add hl,hl \\ add hl,hl \\ add hl,hl \\ add hl,hl",
        "destroys": "HL",
        "input": "HL=i1=uint16",
        "ir": "7 <<",
        "output": "cf:HL=o1=uint17",
        "requires": "",
        "size": 7,
        "speed": 77,
        "state": ""
    },
    {
        "code": "ld h,l \\ ld l,0",
        "destroys": "HL",
        "input": "HL=i1=uint16",
        "ir": "8 <<",
        "output": "cf:HL=o1=uint17",
        "requires": "",
        "size": 3,
        "speed": 11,
        "state": ""
    },
    {
        "code": "ld h,l \\ ld l,0 \\ add hl,hl",
        "destroys": "HL",
        "input": "HL=i1=uint16",
        "ir": "9 <<",
        "output": "cf:HL=o1=uint17",
        "requires": "",
        "size": 4,
        "speed": 22,
        "state": ""
    },
    {
        "code": "sra h \\ ld h,l \\ rr h \\ ld l,0 \\ rr l",
        "destroys": "HL",
        "input": "HL=i1=uint16",
        "ir": "7 <<",
        "output": "cf:HL=o1=uint17",
        "requires": "",
        "size": 9,
        "speed": 35,
        "state": ""
    },
    {
        "code": "ld h,l \\ ld l,0 \\ add hl,hl \\ add hl,hl",
        "destroys": "HL",
        "input": "HL=i1=uint16",
        "ir": "10 <<",
        "output": "cf:HL=o1=uint17",
        "requires": "",
        "size": 5,
        "speed": 33,
        "state": ""
    },
    {
        "code": "jq(**)",
        "destroys": "",
        "input": "",
        "ir": "Goto(",
        "output": "",
        "requires": "",
        "size": 3,
        "speed": 10,
        "state": ""
    },
    {
        "code": "ld a,h \\ or l \\ jqnz(**)",
        "destroys": "AF,HL",
        "input": "HL=i1=uint16",
        "ir": "GotoIf(",
        "output": "",
        "requires": "",
        "size": 5,
        "speed": 18,
        "state": ""
    },
    {
        "code": "ld a,h \\ or l \\ jqz(**)",
        "destroys": "AF,HL",
        "input": "HL=i1=uint16",
        "ir": "GotoIfNot(",
        "output": "",
        "requires": "",
        "size": 5,
        "speed": 18,
        "state": ""
    },
    {
        "code": "xor a \\ sbc hl,de \\ ld h,a \\ ld l,a \\ jr nz,$+3 \\ inc l",
        "destroys": "HL,AF",
        "input": "HL=i1=uint16,DE=i2=uint16",
        "ir": "=",
        "output": "HL=o1=uint16",
        "requires": "",
        "size": 8,
        "speed": 38.5,
        "state": ""
    },
    {
        "code": "xor a \\ sbc hl,bc \\ ld h,a \\ ld l,a \\ jr nz,$+3 \\ inc l",
        "destroys": "HL,AF",
        "input": "HL=i1=uint16,BC=i2=uint16",
        "ir": "=",
        "output": "HL=o1=uint16",
        "requires": "",
        "size": 8,
        "speed": 38.5,
        "state": ""
    },
    {
        "code": "xor a \\ sbc hl,de \\ ld h,a \\ ld l,a \\ jr nz,$+3 \\ inc l",
        "destroys": "HL,AF",
        "input": "DE=i1=uint16,HL=i2=uint16",
        "ir": "=",
        "output": "HL=o1=uint16",
        "requires": "",
        "size": 8,
        "speed": 38.5,
        "state": ""
    },
    {
        "code": "xor a \\ sbc hl,bc \\ ld h,a \\ ld l,a \\ jr nz,$+3 \\ inc l",
        "destroys": "HL,AF",
        "input": "BC=i1=uint16,HL=i2=uint16",
        "ir": "=",
        "output": "HL=o1=uint16",
        "requires": "",
        "size": 8,
        "speed": 38.5,
        "state": ""
    },
    {
        "code": "ld a,h \\ or l \\ ld hl,0 \\ jr z,$+3 \\ inc l",
        "destroys": "HL,AF",
        "input": "HL=i1=uint16",
        "ir": "0 =",
        "output": "HL=o1=uint16",
        "requires": "",
        "size": 8,
        "speed": 29.5,
        "state": ""
    },
    {
        "code": "ld a,d \\ or e \\ ld hl,0 \\ jr z,$+3 \\ inc l",
        "destroys": "HL,AF",
        "input": "DE=i1=uint16",
        "ir": "0 =",
        "output": "HL=o1=uint16",
        "requires": "",
        "size": 8,
        "speed": 29.5,
        "state": ""
    },
    {
        "code": "ld a,b \\ or c \\ ld hl,0 \\ jr z,$+3 \\ inc l",
        "destroys": "HL,AF",
        "input": "BC=i1=uint16",
        "ir": "0 =",
        "output": "HL=o1=uint16",
        "requires": "",
        "size": 8,
        "speed": 29.5,
        "state": ""
    },
    {
        "code": "ld a,ixh \\ or ixl \\ ld hl,0 \\ jr z,$+3 \\ inc l",
        "destroys": "HL,AF",
        "input": "IX=i1=uint16",
        "ir": "0 =",
        "output": "HL=o1=uint16",
        "requires": "",
        "size": 10,
        "speed": 37.5,
        "state": ""
    },
    {
        "code": "ld a,h \\ or l \\ jqz(**)",
        "destroys": "AF",
        "input": "HL=i1=uint16",
        "ir": "0 = GotoIf(",
        "output": "",
        "requires": "",
        "size": 5,
        "speed": 17.75,
        "state": ""
    },
    {
        "code": "ld a,d \\ or e \\ jqz(**)",
        "destroys": "AF",
        "input": "DE=i1=uint16",
        "ir": "0 = GotoIf(",
        "output": "",
        "requires": "",
        "size": 5,
        "speed": 17.75,
        "state": ""
    },
    {
        "code": "ld a,b \\ or c \\ jqz(**)",
        "destroys": "AF",
        "input": "BC=i1=uint16",
        "ir": "0 = GotoIf(",
        "output": "",
        "requires": "",
        "size": 5,
        "speed": 17.75,
        "state": ""
    },
    {
        "code": "ld a,ixh \\ or ixl \\ jqz(**)",
        "destroys": "AF",
        "input": "IX=i1=uint16",
        "ir": "0 = GotoIf(",
        "output": "",
        "requires": "",
        "size": 7,
        "speed": 25.75,
        "state": ""
    },
    {
        "code": "ld a,h \\ or l \\ jqnz(**)",
        "destroys": "AF",
        "input": "HL=i1=uint16",
        "ir": "0 = GotoIfNot(",
        "output": "",
        "requires": "",
        "size": 5,
        "speed": 17.75,
        "state": ""
    },
    {
        "code": "ld a,d \\ or e \\ jqnz(**)",
        "destroys": "AF",
        "input": "DE=i1=uint16",
        "ir": "0 = GotoIfNot(",
        "output": "",
        "requires": "",
        "size": 5,
        "speed": 17.75,
        "state": ""
    },
    {
        "code": "ld a,b \\ or c \\ jqnz(**)",
        "destroys": "AF",
        "input": "BC=i1=uint16",
        "ir": "0 = GotoIfNot(",
        "output": "",
        "requires": "",
        "size": 5,
        "speed": 17.75,
        "state": ""
    },
    {
        "code": "ld a,ixh \\ or ixl \\ jqnz(**)",
        "destroys": "AF",
        "input": "IX=i1=uint16",
        "ir": "0 = GotoIfNot(",
        "output": "",
        "requires": "",
        "size": 7,
        "speed": 25.75,
        "state": ""
    },
    {
        "code": "xor a \\ sbc hl,de \\ ld h,a \\ ld l,a \\ jr z,$+3 \\ inc l",
        "destroys": "HL,AF",
        "input": "HL=i1=uint16,DE=i2=uint16",
        "ir": "!=",
        "output": "HL=o1=uint16",
        "requires": "",
        "size": 8,
        "speed": 38.5,
        "state": ""
    },
    {
        "code": "xor a \\ sbc hl,bc \\ ld h,a \\ ld l,a \\ jr z,$+3 \\ inc l",
        "destroys": "HL,AF",
        "input": "HL=i1=uint16,BC=i2=uint16",
        "ir": "!=",
        "output": "HL=o1=uint16",
        "requires": "",
        "size": 8,
        "speed": 38.5,
        "state": ""
    },
    {
        "code": "xor a \\ sbc hl,de \\ ld h,a \\ ld l,a \\ jr z,$+3 \\ inc l",
        "destroys": "HL,AF",
        "input": "DE=i1=uint16,HL=i2=uint16",
        "ir": "!=",
        "output": "HL=o1=uint16",
        "requires": "",
        "size": 8,
        "speed": 38.5,
        "state": ""
    },
    {
        "code": "xor a \\ sbc hl,bc \\ ld h,a \\ ld l,a \\ jr z,$+3 \\ inc l",
        "destroys": "HL,AF",
        "input": "BC=i1=uint16,HL=i2=uint16",
        "ir": "!=",
        "output": "HL=o1=uint16",
        "requires": "",
        "size": 8,
        "speed": 38.5,
        "state": ""
    },
    {
        "code": "ld a,h \\ or l \\ ld hl,0 \\ jr nz,$+3 \\ inc l",
        "destroys": "HL,AF",
        "input": "HL=i1=uint16",
        "ir": "0 !=",
        "output": "HL=o1=uint16",
        "requires": "",
        "size": 8,
        "speed": 29.5,
        "state": ""
    },
    {
        "code": "ld a,d \\ or e \\ ld hl,0 \\ jr nz,$+3 \\ inc l",
        "destroys": "HL,AF",
        "input": "DE=i1=uint16",
        "ir": "0 !=",
        "output": "HL=o1=uint16",
        "requires": "",
        "size": 8,
        "speed": 29.5,
        "state": ""
    },
    {
        "code": "ld a,b \\ or c \\ ld hl,0 \\ jr nz,$+3 \\ inc l",
        "destroys": "HL,AF",
        "input": "BC=i1=uint16",
        "ir": "0 !=",
        "output": "HL=o1=uint16",
        "requires": "",
        "size": 8,
        "speed": 29.5,
        "state": ""
    },
    {
        "code": "ld a,ixh \\ or ixl \\ ld hl,0 \\ jr nz,$+3 \\ inc l",
        "destroys": "HL,AF",
        "input": "IX=i1=uint16",
        "ir": "0 !=",
        "output": "HL=o1=uint16",
        "requires": "",
        "size": 10,
        "speed": 37.5,
        "state": ""
    },
    {
        "code": "ld a,h \\ or l \\ jqnz(**)",
        "destroys": "AF",
        "input": "HL=i1=uint16",
        "ir": "0 != GotoIf(",
        "output": "",
        "requires": "",
        "size": 5,
        "speed": 17.75,
        "state": ""
    },
    {
        "code": "ld a,d \\ or e \\ jqnz(**)",
        "destroys": "AF",
        "input": "DE=i1=uint16",
        "ir": "0 != GotoIf(",
        "output": "",
        "requires": "",
        "size": 5,
        "speed": 17.75,
        "state": ""
    },
    {
        "code": "ld a,b \\ or c \\ jqnz(**)",
        "destroys": "AF",
        "input": "BC=i1=uint16",
        "ir": "0 != GotoIf(",
        "output": "",
        "requires": "",
        "size": 5,
        "speed": 17.75,
        "state": ""
    },
    {
        "code": "ld a,ixh \\ or ixl \\ jqnz(**)",
        "destroys": "AF",
        "input": "IX=i1=uint16",
        "ir": "0 != GotoIf(",
        "output": "",
        "requires": "",
        "size": 7,
        "speed": 25.75,
        "state": ""
    },
    {
        "code": "ld a,h \\ or l \\ jqz(**)",
        "destroys": "AF",
        "input": "HL=i1=uint16",
        "ir": "0 != GotoIfNot(",
        "output": "",
        "requires": "",
        "size": 5,
        "speed": 17.75,
        "state": ""
    },
    {
        "code": "ld a,d \\ or e \\ jqz(**)",
        "destroys": "AF",
        "input": "DE=i1=uint16",
        "ir": "0 != GotoIfNot(",
        "output": "",
        "requires": "",
        "size": 5,
        "speed": 17.75,
        "state": ""
    },
    {
        "code": "ld a,b \\ or c \\ jqz(**)",
        "destroys": "AF",
        "input": "BC=i1=uint16",
        "ir": "0 != GotoIfNot(",
        "output": "",
        "requires": "",
        "size": 5,
        "speed": 17.75,
        "state": ""
    },
    {
        "code": "ld a,ixh \\ or ixl \\ jqz(**)",
        "destroys": "AF",
        "input": "IX=i1=uint16",
        "ir": "0 != GotoIfNot(",
        "output": "",
        "requires": "",
        "size": 7,
        "speed": 25.75,
        "state": ""
    },
    {
        "code": "dec hl",
        "destroys": "HL",
        "input": "HL=i1=uint16",
        "ir": "--",
        "output": "HL=o1=uint16",
        "requires": "",
        "size": 1,
        "speed": 6,
        "state": ""
    },
    {
        "code": "dec de",
        "destroys": "DE",
        "input": "DE=i1=uint16",
        "ir": "--",
        "output": "DE=o1=uint16",
        "requires": "",
        "size": 1,
        "speed": 6,
        "state": ""
    },
    {
        "code": "dec bc",
        "destroys": "BC",
        "input": "BC=i1=uint16",
        "ir": "--",
        "output": "BC=o1=uint16",
        "requires": "",
        "size": 1,
        "speed": 6,
        "state": ""
    },
    {
        "code": "dec ix",
        "destroys": "IX",
        "input": "IX=i1=uint16",
        "ir": "--",
        "output": "IX=o1=uint16",
        "requires": "",
        "size": 2,
        "speed": 10,
        "state": ""
    },
    {
        "code": "call sprite8",
        "destroys": "AF,BC,DE,HL",
        "input": "DE=i4=uint16,A=i3=uint8,C=i2=int8,B=i1=int8",
        "ir": "Sprite8(",
        "output": "",
        "requires": "#include \"sprite8.z80\"",
        "size": 3,
        "speed": 17,
        "state": ""
    },
    {
        "code": "call UpdateLCD",
        "destroys": "",
        "input": "",
        "ir": "UpdateLCD(",
        "output": "",
        "requires": "#include \"UpdateLCD.z80\"",
        "size": 3,
        "speed": 17,
        "state": ""
    },
    {
        "code": "ld hl,gbuf",
        "destroys": "HL",
        "input": "",
        "ir": "GetGBuf(",
        "output": "HL=o1=uint16",
        "requires": "#include \"gfx.inc\"",
        "size": 3,
        "speed": 10,
        "state": ""
    },
    {
        "code": "ld (gbuf_ptr),hl",
        "destroys": "",
        "input": "HL=i1=uint16",
        "ir": "SetGBuf(",
        "output": "",
        "requires": "#include \"gfx.inc\"",
        "size": 3,
        "speed": 10,
        "state": ""
    },
    {
        "code": "xor a \\ sub l \\ ld l,a \\ sbc a,a \\ sub h \\ ld h,a",
        "destroys": "HL,AF",
        "input": "HL=i1=uint16",
        "ir": "\\-",
        "output": "HL=o1=uint16",
        "requires": "",
        "size": 6,
        "speed": 24,
        "state": ""
    },
    {
        "code": "xor a \\ sub e \\ ld e,a \\ sbc a,a \\ sub d \\ ld d,a",
        "destroys": "DE,AF",
        "input": "DE=i1=uint16",
        "ir": "\\-",
        "output": "DE=o1=uint16",
        "requires": "",
        "size": 6,
        "speed": 24,
        "state": ""
    },
    {
        "code": "xor a \\ sub c \\ ld c,a \\ sbc a,a \\ sub b \\ ld b,a",
        "destroys": "BC,AF",
        "input": "BC=i1=uint16",
        "ir": "\\-",
        "output": "BC=o1=uint16",
        "requires": "",
        "size": 6,
        "speed": 24,
        "state": ""
    },
    {
        "code": "xor a \\ sub ixl \\ ld ixl,a \\ sbc a,a \\ sub ixh \\ ld ixh,a",
        "destroys": "IX,AF",
        "input": "IX=i1=uint16",
        "ir": "\\-",
        "output": "IX=o1=uint16",
        "requires": "",
        "size": 10,
        "speed": 40,
        "state": ""
    },
    {
        "code": "call getKey",
        "destroys": "AF",
        "input": "",
        "ir": "getKey(",
        "output": "A=o1=uint8",
        "requires": "#include \"getKey.z80\"",
        "size": 3,
        "speed": 17,
        "state": ""
    }
]
